llama_index/tools/cogniswitch/__init__.py
llama_index/tools/cogniswitch/base.py
llama_index_tools_cogniswitch-0.4.1.dist-info/METADATA
llama_index_tools_cogniswitch-0.4.1.dist-info/WHEEL
llama_index_tools_cogniswitch-0.4.1.dist-info/licenses/LICENSE
llama_index_tools_cogniswitch-0.4.1.dist-info/RECORD
