Metadata-Version: 2.4
Name: llama-index-tools-cogniswitch
Version: 0.4.1
Summary: llama-index tools cogniswitch integration
Author-email: Your Name <you@example.com>
Maintainer: cogniswitch
License-Expression: MIT
License-File: LICENSE
Keywords: embedding,graph,knowledge graph,neural,symbolic
Requires-Python: <4.0,>=3.9
Requires-Dist: llama-index-core<0.15,>=0.13.0
